sbovqaopt/__init__.py
sbovqaopt/optimizer/__init__.py
sbovqaopt/optimizer/optimizer.py
sbovqaopt/optimizer/optimizer_iteration.py
sbovqaopt-0.1.0.dist-info/LICENSE
sbovqaopt-0.1.0.dist-info/METADATA
sbovqaopt-0.1.0.dist-info/WHEEL
sbovqaopt-0.1.0.dist-info/top_level.txt
sbovqaopt-0.1.0.dist-info/RECORD
