Metadata-Version: 2.1
Name: sbovqaopt
Version: 0.1.0
Summary: Surrogate-based optimizer for variational quantum algorithms.
Home-page: https://github.com/sandialabs/sbovqaopt
Author: Ryan Shaffer
Author-email: ryan@ryanshaffer.net
License: UNKNOWN
Platform: UNKNOWN
Classifier: Programming Language :: Python :: 3
Classifier: License :: OSI Approved :: MIT License
Classifier: Operating System :: OS Independent
Requires-Python: >=3.6
License-File: LICENSE
Requires-Dist: numpy
Requires-Dist: scipy
Requires-Dist: qiskit
